ozschoolbreaks/__init__.py
ozschoolbreaks/breaks.py
ozschoolbreaks/data.py
ozschoolbreaks/school_breaks.yaml
ozschoolbreaks/utils.py
ozschoolbreaks-0.4.0.dist-info/METADATA
ozschoolbreaks-0.4.0.dist-info/WHEEL
ozschoolbreaks-0.4.0.dist-info/licenses/LICENSE
ozschoolbreaks-0.4.0.dist-info/RECORD
