Metadata-Version: 2.4
Name: ozschoolbreaks
Version: 0.4.0
Summary: A package to get school break dates for Australian states
Project-URL: Homepage, https://github.com/adham/ozschoolbreaks
Project-URL: Repository, https://github.com/adham/ozschoolbreaks
Author-email: Adham Beyki <adhambeyki@gmail.com>
License: MIT License
License-File: LICENSE
Classifier: License :: OSI Approved :: MIT License
Classifier: Operating System :: OS Independent
Classifier: Programming Language :: Python :: 3
Requires-Python: >=3.8
Requires-Dist: pyyaml>=6.0.1
